{
	"info": {
		"_postman_id": "f8fd1533-8f53-4358-9223-c80a8441038f",
		"name": "Requests",
		"schema": "https://schema.getpostman.com/json/collection/v2.1.0/collection.json"
	},
	"item": [
		{
			"name": "CREATE",
			"item": [
				{
					"name": "inserirJogo",
					"item": [
						{
							"name": "TheLastOfUs2",
							"request": {
								"method": "POST",
								"header": [],
								"body": {
									"mode": "raw",
									"raw": "{\n    \"nome\": \"The Last of Us Part II\",\n    \"ano\": \"2020\",\n    \"preco\": \"120.0\",\n    \"genero\": \"Ação-Aventura\",\n    \"idUsuario\": \"1\"\n}",
									"options": {
										"raw": {
											"language": "json"
										}
									}
								},
								"url": {
									"raw": "http://localhost:3000/inserirJogo",
									"protocol": "http",
									"host": [
										"localhost"
									],
									"port": "3000",
									"path": [
										"inserirJogo"
									]
								}
							},
							"response": []
						},
						{
							"name": "TheWitcher3",
							"request": {
								"method": "POST",
								"header": [
									{
										"key": "x-access-token",
										"value": "eyJhbGciOiJIUzI1NiIsInR5cCI6IkpXVCJ9.eyJpZCI6MSwiaWF0IjoxNjQ2OTMwMDE1LCJleHAiOjE2NDY5MzA2MTV9.5t6kF_GHqKI3u3Wl9Z7A8pyXZkS5QKMMciDauRqhwrw",
										"type": "text"
									}
								],
								"body": {
									"mode": "raw",
									"raw": "{\n    \"nome\": \"The Witcher 3: Wild Hunt\",\n    \"ano\": \"2015\",\n    \"preco\": \"60.0\",\n    \"genero\": \"RPG\",\n    \"idUsuario\": \"3\"\n}",
									"options": {
										"raw": {
											"language": "json"
										}
									}
								},
								"url": {
									"raw": "http://localhost:3000/inserirJogo",
									"protocol": "http",
									"host": [
										"localhost"
									],
									"port": "3000",
									"path": [
										"inserirJogo"
									]
								}
							},
							"response": []
						},
						{
							"name": "FIFA22",
							"request": {
								"method": "POST",
								"header": [],
								"body": {
									"mode": "raw",
									"raw": "{\n    \"nome\": \"FIFA 22\",\n    \"ano\": \"2021\",\n    \"preco\": \"200.0\",\n    \"genero\": \"Esporte\",\n    \"idUsuario\": \"3\"\n}",
									"options": {
										"raw": {
											"language": "json"
										}
									}
								},
								"url": {
									"raw": "http://localhost:3000/inserirJogo",
									"protocol": "http",
									"host": [
										"localhost"
									],
									"port": "3000",
									"path": [
										"inserirJogo"
									]
								}
							},
							"response": []
						},
						{
							"name": "TheEldersScrollsV",
							"request": {
								"method": "POST",
								"header": [],
								"body": {
									"mode": "raw",
									"raw": "{\n    \"nome\": \"The Elder Scrolls V: Skyrim\",\n    \"ano\": \"2011\",\n    \"preco\": \"60.0\",\n    \"genero\": \"RPG\",\n    \"idUsuario\": \"4\"\n}",
									"options": {
										"raw": {
											"language": "json"
										}
									}
								},
								"url": {
									"raw": "http://localhost:3000/inserirJogo",
									"protocol": "http",
									"host": [
										"localhost"
									],
									"port": "3000",
									"path": [
										"inserirJogo"
									]
								}
							},
							"response": []
						},
						{
							"name": "JustDance2022",
							"request": {
								"method": "POST",
								"header": [],
								"body": {
									"mode": "raw",
									"raw": "{\n    \"nome\": \"Just Dance 2022\",\n    \"ano\": \"2021\",\n    \"preco\": \"190.0\",\n    \"genero\": \"Música\",\n    \"idUsuario\": \"4\"\n}",
									"options": {
										"raw": {
											"language": "json"
										}
									}
								},
								"url": {
									"raw": "http://localhost:3000/inserirJogo",
									"protocol": "http",
									"host": [
										"localhost"
									],
									"port": "3000",
									"path": [
										"inserirJogo"
									]
								}
							},
							"response": []
						},
						{
							"name": "DonkeyKong",
							"request": {
								"method": "POST",
								"header": [],
								"body": {
									"mode": "raw",
									"raw": "{\n    \"nome\": \"Donkey Kong\",\n    \"ano\": \"1994\",\n    \"preco\": \"130\",\n    \"genero\": \"Plataforma\",\n    \"idUsuario\": \"5\"\n}",
									"options": {
										"raw": {
											"language": "json"
										}
									}
								},
								"url": {
									"raw": "http://localhost:3000/inserirJogo",
									"protocol": "http",
									"host": [
										"localhost"
									],
									"port": "3000",
									"path": [
										"inserirJogo"
									]
								}
							},
							"response": []
						}
					]
				},
				{
					"name": "inserirUsuario",
					"item": [
						{
							"name": "LuisFelipe",
							"request": {
								"method": "POST",
								"header": [],
								"body": {
									"mode": "raw",
									"raw": "{\n    \"nome\": \"Luis Felipe\",\n    \"email\": \"lframos_ferreira@outlook.com\",\n    \"senha\": \"12345\"\n}",
									"options": {
										"raw": {
											"language": "json"
										}
									}
								},
								"url": {
									"raw": "http://localhost:3000/inserirUsuario",
									"protocol": "http",
									"host": [
										"localhost"
									],
									"port": "3000",
									"path": [
										"inserirUsuario"
									]
								}
							},
							"response": []
						},
						{
							"name": "Ivan",
							"request": {
								"method": "POST",
								"header": [],
								"body": {
									"mode": "raw",
									"raw": "{\n    \"nome\": \"Ivan\",\n    \"email\": \"ivan@gmail.com\",\n    \"senha\": \"12543\"\n}",
									"options": {
										"raw": {
											"language": "json"
										}
									}
								},
								"url": {
									"raw": "http://localhost:3000/inserirUsuario",
									"protocol": "http",
									"host": [
										"localhost"
									],
									"port": "3000",
									"path": [
										"inserirUsuario"
									]
								}
							},
							"response": []
						},
						{
							"name": "Gabi",
							"request": {
								"method": "POST",
								"header": [],
								"body": {
									"mode": "raw",
									"raw": "{\n    \"nome\": \"Gabi\",\n    \"email\": \"gabi@email.com\",\n    \"senha\": \"54321\"\n}",
									"options": {
										"raw": {
											"language": "json"
										}
									}
								},
								"url": {
									"raw": "http://localhost:3000/inserirUsuario",
									"protocol": "http",
									"host": [
										"localhost"
									],
									"port": "3000",
									"path": [
										"inserirUsuario"
									]
								}
							},
							"response": []
						},
						{
							"name": "Camacho",
							"request": {
								"method": "POST",
								"header": [],
								"body": {
									"mode": "raw",
									"raw": "{\n    \"nome\": \"Camacho\",\n    \"email\": \"camacho@outlook.com\",\n    \"senha\": \"123456\"\n}",
									"options": {
										"raw": {
											"language": "json"
										}
									}
								},
								"url": {
									"raw": "http://localhost:3000/inserirUsuario",
									"protocol": "http",
									"host": [
										"localhost"
									],
									"port": "3000",
									"path": [
										"inserirUsuario"
									]
								}
							},
							"response": []
						},
						{
							"name": "Gabi Copy",
							"request": {
								"method": "POST",
								"header": [],
								"body": {
									"mode": "raw",
									"raw": "{\n    \"nome\": \"Mara\",\n    \"email\": \"mara@orkut.com\",\n    \"senha\": \"senha\"\n}",
									"options": {
										"raw": {
											"language": "json"
										}
									}
								},
								"url": {
									"raw": "http://localhost:3000/inserirUsuario",
									"protocol": "http",
									"host": [
										"localhost"
									],
									"port": "3000",
									"path": [
										"inserirUsuario"
									]
								}
							},
							"response": []
						}
					]
				}
			]
		},
		{
			"name": "DELETE",
			"item": [
				{
					"name": "JogoID",
					"request": {
						"method": "DELETE",
						"header": [
							{
								"key": "x-access-token",
								"value": "eyJhbGciOiJIUzI1NiIsInR5cCI6IkpXVCJ9.eyJpZCI6MSwiaWF0IjoxNjQ2OTMwMDE1LCJleHAiOjE2NDY5MzA2MTV9.5t6kF_GHqKI3u3Wl9Z7A8pyXZkS5QKMMciDauRqhwrw",
								"type": "text"
							}
						],
						"url": {
							"raw": "http://localhost:3000/deletarJogo/3",
							"protocol": "http",
							"host": [
								"localhost"
							],
							"port": "3000",
							"path": [
								"deletarJogo",
								"3"
							]
						}
					},
					"response": []
				},
				{
					"name": "UsuarioID_1",
					"request": {
						"method": "DELETE",
						"header": [
							{
								"key": "x-access-token",
								"value": "eyJhbGciOiJIUzI1NiIsInR5cCI6IkpXVCJ9.eyJpZCI6MiwiaWF0IjoxNjQ2OTI5NjI2LCJleHAiOjE2NDY5Mjk5MjZ9.hSsWhVvn78mSIo8Ax65PWmSyuvXoLTb0rzVmFPU_T5E",
								"type": "text"
							}
						],
						"url": {
							"raw": "http://localhost:3000/deletarUsuario/2",
							"protocol": "http",
							"host": [
								"localhost"
							],
							"port": "3000",
							"path": [
								"deletarUsuario",
								"2"
							]
						}
					},
					"response": []
				}
			]
		},
		{
			"name": "READ",
			"item": [
				{
					"name": "jogoId",
					"request": {
						"method": "GET",
						"header": [
							{
								"key": "x-access-token",
								"value": "eyJhbGciOiJIUzI1NiIsInR5cCI6IkpXVCJ9.eyJpZCI6MiwiaWF0IjoxNjQ2OTI5NjI2LCJleHAiOjE2NDY5Mjk5MjZ9.hSsWhVvn78mSIo8Ax65PWmSyuvXoLTb0rzVmFPU_T5E",
								"type": "text"
							}
						],
						"url": {
							"raw": "http://localhost:3000/checarJogo/1",
							"protocol": "http",
							"host": [
								"localhost"
							],
							"port": "3000",
							"path": [
								"checarJogo",
								"1"
							]
						}
					},
					"response": []
				},
				{
					"name": "usuarioID",
					"request": {
						"method": "GET",
						"header": [
							{
								"key": "x-access-token",
								"value": "eyJhbGciOiJIUzI1NiIsInR5cCI6IkpXVCJ9.eyJ1c2VySWQiOjEsImlhdCI6MTY0NjkzMjg4MSwiZXhwIjoxNjQ2OTMzNDgxfQ._7t0YcLtdhH0-zTxX74lu5nQLsF5hmVQbMn0ftWUp4Y",
								"type": "text"
							}
						],
						"url": {
							"raw": "http://localhost:3000/checarUsuario/2",
							"protocol": "http",
							"host": [
								"localhost"
							],
							"port": "3000",
							"path": [
								"checarUsuario",
								"2"
							]
						}
					},
					"response": []
				},
				{
					"name": "checarUsuarioJogos",
					"request": {
						"method": "GET",
						"header": [
							{
								"key": "x-access-token",
								"value": "eyJhbGciOiJIUzI1NiIsInR5cCI6IkpXVCJ9.eyJ1c2VySWQiOjEsImlhdCI6MTY0NjkzMjg4MSwiZXhwIjoxNjQ2OTMzNDgxfQ._7t0YcLtdhH0-zTxX74lu5nQLsF5hmVQbMn0ftWUp4Y",
								"type": "text"
							}
						],
						"url": {
							"raw": "http://localhost:3000/checarUsuarioJogos/2",
							"protocol": "http",
							"host": [
								"localhost"
							],
							"port": "3000",
							"path": [
								"checarUsuarioJogos",
								"2"
							]
						}
					},
					"response": []
				}
			]
		},
		{
			"name": "UPDATE",
			"item": [
				{
					"name": "AlterarPrecoId",
					"request": {
						"method": "POST",
						"header": [
							{
								"key": "x-access-token",
								"value": "eyJhbGciOiJIUzI1NiIsInR5cCI6IkpXVCJ9.eyJpZCI6MiwiaWF0IjoxNjQ2OTI5NjI2LCJleHAiOjE2NDY5Mjk5MjZ9.hSsWhVvn78mSIo8Ax65PWmSyuvXoLTb0rzVmFPU_T5E",
								"type": "text"
							}
						],
						"body": {
							"mode": "raw",
							"raw": "{\n    \"id\": \"1\",\n    \"preco\": \"1111\"\n}",
							"options": {
								"raw": {
									"language": "json"
								}
							}
						},
						"url": {
							"raw": "http://localhost:3000/alterarPrecoJogo",
							"protocol": "http",
							"host": [
								"localhost"
							],
							"port": "3000",
							"path": [
								"alterarPrecoJogo"
							]
						}
					},
					"response": []
				},
				{
					"name": "AlterarSenhaMara",
					"request": {
						"method": "POST",
						"header": [
							{
								"key": "x-access-token",
								"value": "eyJhbGciOiJIUzI1NiIsInR5cCI6IkpXVCJ9.eyJpZCI6MiwiaWF0IjoxNjQ2OTI5NjI2LCJleHAiOjE2NDY5Mjk5MjZ9.hSsWhVvn78mSIo8Ax65PWmSyuvXoLTb0rzVmFPU_T5E",
								"type": "text"
							}
						],
						"body": {
							"mode": "raw",
							"raw": "{\n    \"id\": \"1\",\n    \"senha\": \"senhaMaisForte\"\n}",
							"options": {
								"raw": {
									"language": "json"
								}
							}
						},
						"url": {
							"raw": "http://localhost:3000/alterarSenhaUsuario",
							"protocol": "http",
							"host": [
								"localhost"
							],
							"port": "3000",
							"path": [
								"alterarSenhaUsuario"
							]
						}
					},
					"response": []
				}
			]
		},
		{
			"name": "usuario",
			"item": [
				{
					"name": "login",
					"request": {
						"method": "POST",
						"header": [],
						"body": {
							"mode": "raw",
							"raw": "{\n    \"email\": \"lframos_ferreira@outlook.com\",\n    \"senha\": \"senhaMaisForte\"\n}",
							"options": {
								"raw": {
									"language": "json"
								}
							}
						},
						"url": {
							"raw": "http://localhost:3000/usuario/login",
							"protocol": "http",
							"host": [
								"localhost"
							],
							"port": "3000",
							"path": [
								"usuario",
								"login"
							]
						}
					},
					"response": []
				},
				{
					"name": "logout",
					"request": {
						"method": "POST",
						"header": [
							{
								"key": "x-access-token",
								"value": "eyJhbGciOiJIUzI1NiIsInR5cCI6IkpXVCJ9.eyJ1c2VySWQiOjEsImlhdCI6MTY0NjkzMTU5NywiZXhwIjoxNjQ2OTMyMTk3fQ.PaaxzEalCRmb-qvg_YuXU6HaxYpdfXLiWk5rccXXoBI",
								"type": "text"
							}
						],
						"url": {
							"raw": "http://localhost:3000/usuario/logout",
							"protocol": "http",
							"host": [
								"localhost"
							],
							"port": "3000",
							"path": [
								"usuario",
								"logout"
							]
						}
					},
					"response": []
				}
			]
		}
	]
}